pyhafas/__init__.py
pyhafas/client.py
pyhafas/profile/__init__.py
pyhafas/profile/base/__init__.py
pyhafas/profile/base/helper/__init__.py
pyhafas/profile/base/helper/date_time.py
pyhafas/profile/base/helper/format_products_filter.py
pyhafas/profile/base/helper/parse_leg.py
pyhafas/profile/base/helper/parse_lid.py
pyhafas/profile/base/helper/parse_remark.py
pyhafas/profile/base/helper/request.py
pyhafas/profile/base/mappings/__init__.py
pyhafas/profile/base/mappings/error_codes.py
pyhafas/profile/base/requests/__init__.py
pyhafas/profile/base/requests/journey.py
pyhafas/profile/base/requests/journeys.py
pyhafas/profile/base/requests/location.py
pyhafas/profile/base/requests/nearby.py
pyhafas/profile/base/requests/station_board.py
pyhafas/profile/base/requests/trip.py
pyhafas/profile/db/__init__.py
pyhafas/profile/interfaces/__init__.py
pyhafas/profile/interfaces/helper/__init__.py
pyhafas/profile/interfaces/helper/date_time.py
pyhafas/profile/interfaces/helper/format_products_filter.py
pyhafas/profile/interfaces/helper/parse_leg.py
pyhafas/profile/interfaces/helper/parse_lid.py
pyhafas/profile/interfaces/helper/parse_remark.py
pyhafas/profile/interfaces/helper/request.py
pyhafas/profile/interfaces/mappings/__init__.py
pyhafas/profile/interfaces/mappings/error_codes.py
pyhafas/profile/interfaces/requests/__init__.py
pyhafas/profile/interfaces/requests/journey.py
pyhafas/profile/interfaces/requests/journeys.py
pyhafas/profile/interfaces/requests/location.py
pyhafas/profile/interfaces/requests/nearby.py
pyhafas/profile/interfaces/requests/station_board.py
pyhafas/profile/interfaces/requests/trip.py
pyhafas/profile/kvb/__init__.py
pyhafas/profile/kvb/requests/__init__.py
pyhafas/profile/kvb/requests/journey.py
pyhafas/profile/kvb/requests/journeys.py
pyhafas/profile/nasa/__init__.py
pyhafas/profile/nasa/requests/__init__.py
pyhafas/profile/nasa/requests/journey.py
pyhafas/profile/nasa/requests/journeys.py
pyhafas/profile/nvv/__init__.py
pyhafas-0.6.1.dist-info/LICENSE
pyhafas-0.6.1.dist-info/METADATA
pyhafas-0.6.1.dist-info/WHEEL
pyhafas-0.6.1.dist-info/top_level.txt
pyhafas-0.6.1.dist-info/zip-safe
pyhafas-0.6.1.dist-info/RECORD
