Metadata-Version: 2.2
Name: pyhafas
Version: 0.6.1
Summary: Python client for HAFAS public transport APIs
Home-page: https://github.com/FahrplanDatenGarten/pyhafas
Download-URL: https://github.com/FahrplanDatenGarten/pyhafas/releases
Author: Ember Keske, Leona Maroni
Author-email: dev@n0emis.eu, dev@leona.is
License: MIT
Classifier: Development Status :: 4 - Beta
Classifier: Intended Audience :: Developers
Classifier: License :: OSI Approved :: MIT License
Classifier: Operating System :: OS Independent
Classifier: Programming Language :: Python :: 3.6
Classifier: Programming Language :: Python :: 3.7
Classifier: Programming Language :: Python :: 3.8
Classifier: Topic :: Utilities
License-File: LICENSE
Requires-Dist: requests~=2.9
Requires-Dist: pytz>=2013.6
Dynamic: author
Dynamic: author-email
Dynamic: classifier
Dynamic: description
Dynamic: description-content-type
Dynamic: download-url
Dynamic: home-page
Dynamic: license
Dynamic: requires-dist
Dynamic: summary
